devinci_pybuilder/__init__.py
devinci_pybuilder/builder.py
devinci_pybuilder/devinci_pybuilder.py
devinci_pybuilder/file_utils.py
devinci_pybuilder/main.py
devinci_pybuilder/build_chores/__init__.py
devinci_pybuilder/build_chores/custom_install_command.py
devinci_pybuilder/stub/example-config.ini
devinci_pybuilder-0.1.0.data/scripts/builder.py
devinci_pybuilder-0.1.0.data/scripts/file_utils.py
devinci_pybuilder-0.1.0.data/scripts/main.py
devinci_pybuilder-0.1.0.dist-info/LICENSE.md
devinci_pybuilder-0.1.0.dist-info/METADATA
devinci_pybuilder-0.1.0.dist-info/WHEEL
devinci_pybuilder-0.1.0.dist-info/dependency_links.txt
devinci_pybuilder-0.1.0.dist-info/entry_points.txt
devinci_pybuilder-0.1.0.dist-info/top_level.txt
devinci_pybuilder-0.1.0.dist-info/RECORD
