Metadata-Version: 2.1
Name: devinci-pybuilder
Version: 0.1.0
Summary: devinci_pybuilder is a Python package builder for managing project setup and generating setup.py files.
Author: devinci-it
License: MIT
License-File: LICENSE.md
Requires-Dist: devinci-pyutils
